{
  "url": "https://books.toscrape.com/catalogue/a-light-in-the-attic_1000/index.html",
  "title": "A Light in the Attic | Books to Scrape - Sandbox",
  "links": [
    "https://books.toscrape.com/catalogue/category/books/poetry_23/index.html",
    "https://books.toscrape.com/index.html",
    "https://books.toscrape.com/catalogue/category/books_1/index.html"
  ],
  "tokens": [
    "home",
    "book",
    "poetri",
    "light",
    "attic",
    "light",
    "attic",
    "stock",
    "avail",
    "warn",
    "demo",
    "websit",
    "web",
    "scrape",
    "purpos",
    "price",
    "rate",
    "randomli",
    "assign",
    "real",
    "mean",
    "product",
    "descript",
    "hard",
    "imagin",
    "world",
    "without",
    "light",
    "attic",
    "classic",
    "collect",
    "poetri",
    "draw",
    "shel",
    "silverstein",
    "celebr",
    "th",
    "anniversari",
    "special",
    "edit",
    "silverstein",
    "humor",
    "creativ",
    "vers",
    "amus",
    "dowdiest",
    "reader",
    "lemon",
    "face",
    "adult",
    "fidgeti",
    "kid",
    "sit",
    "still",
    "read",
    "rhythmic",
    "word",
    "laugh",
    "smile",
    "love",
    "th",
    "hard",
    "imagin",
    "world",
    "without",
    "light",
    "attic",
    "classic",
    "collect",
    "poetri",
    "draw",
    "shel",
    "silverstein",
    "celebr",
    "th",
    "anniversari",
    "special",
    "edit",
    "silverstein",
    "humor",
    "creativ",
    "vers",
    "amus",
    "dowdiest",
    "reader",
    "lemon",
    "face",
    "adult",
    "fidgeti",
    "kid",
    "sit",
    "still",
    "read",
    "rhythmic",
    "word",
    "laugh",
    "smile",
    "love",
    "silverstein",
    "need",
    "proof",
    "geniu",
    "rockabyerockaby",
    "babi",
    "treetopdon",
    "know",
    "treetopi",
    "safe",
    "place",
    "rock",
    "put",
    "cradl",
    "babi",
    "think",
    "someon",
    "sgot",
    "shel",
    "never",
    "sound",
    "good",
    "product",
    "inform",
    "upc",
    "fe",
    "b",
    "product",
    "type",
    "book",
    "price",
    "excl",
    "tax",
    "price",
    "incl",
    "tax",
    "tax",
    "avail",
    "stock",
    "avail",
    "number",
    "review"
  ],
  "token_count": 140
}